pipcontrol/__init__.py
pipcontrol/pipcontrol.py
pipcontrol/test.py
pipcontrol-1.2.1.dist-info/METADATA
pipcontrol-1.2.1.dist-info/WHEEL
pipcontrol-1.2.1.dist-info/top_level.txt
pipcontrol-1.2.1.dist-info/RECORD
