Metadata-Version: 2.1
Name: pipcontrol
Version: 1.2.1
Summary: control pip module in python code
Home-page: https://github.com/labov/pipcontrol
Author: Mingoo Lee
Author-email: labovming@gmail.com
License: MIT
Platform: UNKNOWN
Classifier: Development Status :: 4 - Beta
Classifier: Intended Audience :: Developers
Classifier: Topic :: Software Development :: Build Tools
Classifier: Topic :: Software Development :: Libraries :: Python Modules
Classifier: License :: OSI Approved :: MIT License
Classifier: Programming Language :: Python :: 3.8
Classifier: Operating System :: OS Independent
Requires-Python: >=3.8
